[
    {
        "name": "Palace",  
        "isNationalWonder": true,
		"culture": 1,
		"production": 5,
		"science": 2,
		"cost": 1,
        "uniques": ["Indicates the capital city","[-1 Gold] from every [River]","[+1 Food] from every [River]"]
    },
	
	
	//Faction Specials
	
	//Ardent Mage Pillars
	{
        "name": "Pillar of Knowledge",  
		"uniqueTo": "Ardent Mages",
        "isNationalWonder": true,
		"cost": 75,
        "hurryCostModifier": 20,
        "uniques": ["[+1 Science] from [Grassland] tiles in this city","[+1 Science] from [Plains] tiles in this city","[+1 Science] from [Desert] tiles in this city","[+1 Science] from [Hill] tiles in this city","[+1 Science] from [Tundra] tiles in this city","[+1 Science] from [Snow] tiles in this city",
		"[+3 Science] once [Dust Purifier] is discovered"],
        "requiredTech": "Arcana of Matter"
    },
	{
        "name": "Pillar of Knowledge II",  
		"uniqueTo": "Ardent Mages",
        "isNationalWonder": true,
		"cost": 120,
        "hurryCostModifier": 20,
        "uniques": ["[+1 Science] from [Grassland] tiles in this city","[+1 Science] from [Plains] tiles in this city","[+1 Science] from [Desert] tiles in this city","[+1 Science] from [Hill] tiles in this city","[+1 Science] from [Tundra] tiles in this city","[+1 Science] from [Snow] tiles in this city",
		"[+3 Science] once [Secrets of the Virtuals] is discovered","Requires a [Pillar of Knowledge] in this city"],
        "requiredTech": "Dust Mechanics"
    },
	{
        "name": "Pillar of Knowledge III",  
		"uniqueTo": "Ardent Mages",
        "isNationalWonder": true,
		"cost": 175,
        "hurryCostModifier": 20,
        "uniques": ["[+1 Science] from [Grassland] tiles in this city","[+1 Science] from [Plains] tiles in this city","[+1 Science] from [Desert] tiles in this city","[+1 Science] from [Hill] tiles in this city","[+1 Science] from [Tundra] tiles in this city","[+1 Science] from [Snow] tiles in this city",
		"[+3 Science] once [Secrets of the Virtuals] is discovered","Requires a [Pillar of Knowledge II] in this city"],
        "requiredTech": "Secrets of the Virtuals"
    },
	{
        "name": "Pillar of Knowledge IV",  
		"uniqueTo": "Ardent Mages",
        "isNationalWonder": true,
		"cost": 240,
        "hurryCostModifier": 20,
        "uniques": ["[+1 Science] from [Grassland] tiles in this city","[+1 Science] from [Plains] tiles in this city","[+1 Science] from [Desert] tiles in this city","[+1 Science] from [Hill] tiles in this city","[+1 Science] from [Tundra] tiles in this city","[+1 Science] from [Snow] tiles in this city",
		"[+3 Science] once [Painosphere] is discovered","Requires a [Pillar of Knowledge III] in this city"],
        "requiredTech": "Secrets of the Virtuals"
    },
	{
        "name": "Pillar of Knowledge V",  
		"uniqueTo": "Ardent Mages",
        "isNationalWonder": true,
		"cost": 275,
        "hurryCostModifier": 20,
        "uniques": ["[+1 Science] from [Grassland] tiles in this city","[+1 Science] from [Plains] tiles in this city","[+1 Science] from [Desert] tiles in this city","[+1 Science] from [Hill] tiles in this city","[+1 Science] from [Tundra] tiles in this city","[+1 Science] from [Snow] tiles in this city",
		"Requires a [Pillar of Knowledge IV] in this city"],
        "requiredTech": "Sacrificial Amplifiers"
    },
	{
        "name": "Pillar of Speed",  
		"uniqueTo": "Ardent Mages",
        "isNationalWonder": true,
		"cost": 75,
        "hurryCostModifier": 20,
        "uniques": ["+[1] Movement for all [Military] units"],
		"requiredTech": "Arcana of Agility"
    },
	{
        "name": "Pillar of Speed II",  
		"uniqueTo": "Ardent Mages",
        "isNationalWonder": true,
		"cost": 120,
        "hurryCostModifier": 20,
        "uniques": ["+[1] Movement for all [Military] units",
		"Requires a [Pillar of Speed] in this city"],
        "requiredTech": "Dust Mechanics"
    },
	{
        "name": "Pillar of Speed III",  
		"uniqueTo": "Ardent Mages",
        "isNationalWonder": true,
		"cost": 175,
        "hurryCostModifier": 20,
        "uniques": ["+[1] Movement for all [Military] units",
		"Requires a [Pillar of Speed II] in this city"],
        "requiredTech": "Secrets of the Virtuals"
    },
	{
        "name": "Pillar of Speed IV",  
		"uniqueTo": "Ardent Mages",
        "isNationalWonder": true,
		"cost": 240,
        "hurryCostModifier": 20,
        "uniques": ["+[1] Movement for all [Military] units",
		"Requires a [Pillar of Speed III] in this city"],
        "requiredTech": "Secrets of the Virtuals"
    },
	{
        "name": "Pillar of Speed V",  
		"uniqueTo": "Ardent Mages",
        "isNationalWonder": true,
		"cost": 275,
        "hurryCostModifier": 20,
        "uniques": ["+[1] Movement for all [Military] units",
		"Requires a [Pillar of Speed IV] in this city"],
        "requiredTech": "Sacrificial Amplifiers"
    },
	{
        "name": "Pillar of Influence",  
		"uniqueTo": "Ardent Mages",
        "isNationalWonder": true,
		"cost": 75,
        "hurryCostModifier": 20,
        "uniques": ["[+1 Culture] from [Grassland] tiles in this city","[+1 Culture] from [Plains] tiles in this city","[+1 Culture] from [Desert] tiles in this city","[+1 Culture] from [Hill] tiles in this city","[+1 Culture] from [Tundra] tiles in this city","[+1 Culture] from [Snow] tiles in this city",
		"[+3 Culture] once [Dust Mechanics] is discovered"],
		"requiredTech": "Arcana of Authority"
    },
	{
        "name": "Pillar of Influence II",  
		"uniqueTo": "Ardent Mages",
        "isNationalWonder": true,
		"cost": 120,
        "hurryCostModifier": 20,
        "uniques": ["[+1 Culture] from [Grassland] tiles in this city","[+1 Culture] from [Plains] tiles in this city","[+1 Culture] from [Desert] tiles in this city","[+1 Culture] from [Hill] tiles in this city","[+1 Culture] from [Tundra] tiles in this city","[+1 Culture] from [Snow] tiles in this city",
		"[+3 Culture] once [Secrets of the Virtuals] is discovered","Requires a [Pillar of Influence] in this city"],
        "requiredTech": "Dust Mechanics"
    },
	{
        "name": "Pillar of Influence III",  
		"uniqueTo": "Ardent Mages",
        "isNationalWonder": true,
		"cost": 175,
        "hurryCostModifier": 20,
        "uniques": ["[+1 Culture] from [Grassland] tiles in this city","[+1 Culture] from [Plains] tiles in this city","[+1 Culture] from [Desert] tiles in this city","[+1 Culture] from [Hill] tiles in this city","[+1 Culture] from [Tundra] tiles in this city","[+1 Culture] from [Snow] tiles in this city",
		"[+3 Culture] once [Secrets of the Virtuals] is discovered","Requires a [Pillar of Influence II] in this city"],
        "requiredTech": "Secrets of the Virtuals"
    },
	{
        "name": "Pillar of Influence IV",  
		"uniqueTo": "Ardent Mages",
        "isNationalWonder": true,
		"cost": 240,
        "hurryCostModifier": 20,
        "uniques": ["[+1 Culture] from [Grassland] tiles in this city","[+1 Culture] from [Plains] tiles in this city","[+1 Culture] from [Desert] tiles in this city","[+1 Culture] from [Hill] tiles in this city","[+1 Culture] from [Tundra] tiles in this city","[+1 Culture] from [Snow] tiles in this city",
		"[+3 Culture] once [Painosphere] is discovered","Requires a [Pillar of Influence III] in this city"],
        "requiredTech": "Secrets of the Virtuals"
    },
	{
        "name": "Pillar of Influence V",  
		"uniqueTo": "Ardent Mages",
        "isNationalWonder": true,
		"cost": 275,
        "hurryCostModifier": 20,
        "uniques": ["[+1 Culture] from [Grassland] tiles in this city","[+1 Culture] from [Plains] tiles in this city","[+1 Culture] from [Desert] tiles in this city","[+1 Culture] from [Hill] tiles in this city","[+1 Culture] from [Tundra] tiles in this city","[+1 Culture] from [Snow] tiles in this city",
		"Requires a [Pillar of Influence IV] in this city"],
        "requiredTech": "Sacrificial Amplifiers"
    },
	{
        "name": "Pillar of Extraction",  
		"uniqueTo": "Ardent Mages",
        "isNationalWonder": true,
		"cost": 75,
        "hurryCostModifier": 20,
        "uniques": ["[+1 Gold] from [Grassland] tiles in this city","[+1 Gold] from [Plains] tiles in this city","[+1 Gold] from [Desert] tiles in this city","[+1 Gold] from [Hill] tiles in this city","[+1 Gold] from [Tundra] tiles in this city","[+1 Gold] from [Snow] tiles in this city",
		"[+3 Gold] once [Dust Mechanics] is discovered"],
		"requiredTech": "Arcana of Materializing"
    },
	{
        "name": "Pillar of Extraction II",  
		"uniqueTo": "Ardent Mages",
        "isNationalWonder": true,
		"cost": 120,
        "hurryCostModifier": 20,
        "uniques": ["[+1 Gold] from [Grassland] tiles in this city","[+1 Gold] from [Plains] tiles in this city","[+1 Gold] from [Desert] tiles in this city","[+1 Gold] from [Hill] tiles in this city","[+1 Gold] from [Tundra] tiles in this city","[+1 Gold] from [Snow] tiles in this city",
		"[+3 Gold] once [Secrets of the Virtuals] is discovered","Requires a [Pillar of Extraction] in this city"],
        "requiredTech": "Dust Mechanics"
    },
	{
        "name": "Pillar of Extraction III",  
		"uniqueTo": "Ardent Mages",
        "isNationalWonder": true,
		"cost": 175,
        "hurryCostModifier": 20,
        "uniques": ["[+1 Gold] from [Grassland] tiles in this city","[+1 Gold] from [Plains] tiles in this city","[+1 Gold] from [Desert] tiles in this city","[+1 Gold] from [Hill] tiles in this city","[+1 Gold] from [Tundra] tiles in this city","[+1 Gold] from [Snow] tiles in this city",
		"[+3 Gold] once [Secrets of the Virtuals] is discovered","Requires a [Pillar of Extraction II] in this city"],
        "requiredTech": "Secrets of the Virtuals"
    },
	{
        "name": "Pillar of Extraction IV",  
		"uniqueTo": "Ardent Mages",
        "isNationalWonder": true,
		"cost": 240,
        "hurryCostModifier": 20,
        "uniques": ["[+1 Gold] from [Grassland] tiles in this city","[+1 Gold] from [Plains] tiles in this city","[+1 Gold] from [Desert] tiles in this city","[+1 Gold] from [Hill] tiles in this city","[+1 Gold] from [Tundra] tiles in this city","[+1 Gold] from [Snow] tiles in this city",
		"[+3 Gold] once [Painosphere] is discovered","Requires a [Pillar of Extraction III] in this city"],
        "requiredTech": "Secrets of the Virtuals"
    },
	{
        "name": "Pillar of Extraction V",  
		"uniqueTo": "Ardent Mages",
        "isNationalWonder": true,
		"cost": 275,
        "hurryCostModifier": 20,
        "uniques": ["[+1 Gold] from [Grassland] tiles in this city","[+1 Gold] from [Plains] tiles in this city","[+1 Gold] from [Desert] tiles in this city","[+1 Gold] from [Hill] tiles in this city","[+1 Gold] from [Tundra] tiles in this city","[+1 Gold] from [Snow] tiles in this city",
		"Requires a [Pillar of Extraction IV] in this city"],
        "requiredTech": "Sacrificial Amplifiers"
    },
	{
        "name": "Pillar of Regeneration",  
		"uniqueTo": "Ardent Mages",
        "isNationalWonder": true,
		"cost": 75,
        "hurryCostModifier": 20,
        "uniques": ["[+1 Food] from [Grassland] tiles in this city","[+1 Food] from [Plains] tiles in this city","[+1 Food] from [Desert] tiles in this city","[+1 Food] from [Hill] tiles in this city","[+1 Food] from [Tundra] tiles in this city","[+1 Food] from [Snow] tiles in this city",
		"[+3 Food] once [Dust Mechanics] is discovered"],
		"requiredTech": "Arcana of Renewal"
    },
	{
        "name": "Pillar of Regeneration II",  
		"uniqueTo": "Ardent Mages",
        "isNationalWonder": true,
		"cost": 120,
        "hurryCostModifier": 20,
        "uniques": ["[+1 Food] from [Grassland] tiles in this city","[+1 Food] from [Plains] tiles in this city","[+1 Food] from [Desert] tiles in this city","[+1 Food] from [Hill] tiles in this city","[+1 Food] from [Tundra] tiles in this city","[+1 Food] from [Snow] tiles in this city",
		"[+3 Food] once [Secrets of the Virtuals] is discovered","Requires a [Pillar of Regeneration] in this city"],
		"requiredTech": "Dust Mechanics"
    },
	{
        "name": "Pillar of Regeneration III",  
		"uniqueTo": "Ardent Mages",
        "isNationalWonder": true,
		"cost": 120,
        "hurryCostModifier": 20,
        "uniques": ["[+1 Food] from [Grassland] tiles in this city","[+1 Food] from [Plains] tiles in this city","[+1 Food] from [Desert] tiles in this city","[+1 Food] from [Hill] tiles in this city","[+1 Food] from [Tundra] tiles in this city","[+1 Food] from [Snow] tiles in this city",
		"[+3 Food] once [Secrets of the Virtuals] is discovered","Requires a [Pillar of Regeneration] in this city"],
		"requiredTech": "Secrets of the Virtuals"
    },
	{
        "name": "Pillar of Regeneration IV",  
		"uniqueTo": "Ardent Mages",
        "isNationalWonder": true,
		"cost": 120,
        "hurryCostModifier": 20,
        "uniques": ["[+1 Food] from [Grassland] tiles in this city","[+1 Food] from [Plains] tiles in this city","[+1 Food] from [Desert] tiles in this city","[+1 Food] from [Hill] tiles in this city","[+1 Food] from [Tundra] tiles in this city","[+1 Food] from [Snow] tiles in this city",
		"[+3 Food] once [Painosphere] is discovered","Requires a [Pillar of Regeneration] in this city"],
		"requiredTech": "Secrets of the Virtuals"
    },
	{
        "name": "Pillar of Regeneration V",  
		"uniqueTo": "Ardent Mages",
        "isNationalWonder": true,
		"cost": 120,
        "hurryCostModifier": 20,
        "uniques": ["[+1 Food] from [Grassland] tiles in this city","[+1 Food] from [Plains] tiles in this city","[+1 Food] from [Desert] tiles in this city","[+1 Food] from [Hill] tiles in this city","[+1 Food] from [Tundra] tiles in this city","[+1 Food] from [Snow] tiles in this city",
		"Requires a [Pillar of Regeneration] in this city"],
		"requiredTech": "Sacrificial Amplifiers"
    },
	//rest of Ardent Mage
	{
        "name": "Verda's Temple",     
		"uniqueTo": "Ardent Mages",
        "isNationalWonder": true,
		"cost": 400,
        "hurryCostModifier": 20,
		"uniques": ["[+2 Science] from [Tundra] tiles in this city","[+2 Science] from [Glassteel] tiles in this city","[+2 Science] from [Titanium] tiles in this city","[+2 Science] from [Adamantian] tiles in this city","[+2 Science] from [Palladian] tiles in this city","[+2 Science] from [Mithrite] tiles in this city","[+2 Science] from [Hyperium] tiles in this city",
		"[+2 Science] from [Azotic Exotics] tiles in this city","[+2 Science] from [Black Dust] tiles in this city","[+2 Science] from [Botanical Garden] tiles in this city","[+2 Science] from [Chromatic Land] tiles in this city","[+2 Science] from [Crystal Flowers] tiles in this city","[+2 Science] from [Dragon Tree] tiles in this city","[+2 Science] from [Earthspine] tiles in this city","[+2 Science] from [Earth Tower] tiles in this city","[+2 Science] from [Geothermal Pit] tiles in this city","[+2 Science] from [Geysers] tiles in this city","[+2 Science] from [Ice Sculptures] tiles in this city","[+2 Science] from [Lava Chimneys] tiles in this city","[+2 Science] from [Lava Geyser] tiles in this city","[+2 Science] from [Life Tree] tiles in this city","[+2 Science] from [Meteor Fields] tiles in this city","[+2 Science] from [Moss Pearls] tiles in this city","[+2 Science] from [Mutant Marsh] tiles in this city","[+2 Science] from [Mychordia] tiles in this city","[+2 Science] from [Spiral Rock Peel] tiles in this city","[+2 Science] from [Stasis Pillar] tiles in this city","[+2 Science] from [Wizard Stone] tiles in this city"],
        "requiredTech": "Verda's Temple"
    },
	{
        "name": "Altar of Transcendence",  
		"uniqueTo": "Ardent Mages",
        "isNationalWonder": true,
		"cost": 1000,
		"culture": 10,
		"happiness": 10,
        "hurryCostModifier": 20,
		"uniques": ["[+1 Culture] per [1] population [in this city]"],
        "requiredTech": "Altar of Transcendence"
    },
	//Allayi Tech boost
	{
        "name": "Blessing of the Allayi",  
		"uniqueTo": "Allayi",
        "cityStrength": 25,
        "cityHealth": 50,
		"culture": 2,
		"production": 2,
		"gold": 2,
		"food": 2,
		"science": 2,
		"happiness": -2,
		"cost": 1,
        "uniques": ["Unsellable"],
        "requiredTech": "Garth of the Allayi"
    },
	{
        "name": "Blessing of the Mother",  
		"uniqueTo": "Allayi",
        "isNationalWonder": true,
		"cost": 1,
        "uniques": ["Unsellable","Provides [4] [Glassteel]","Provides [4] [Titanium]","Provides [4] [Adamantian]","Provides [4] [Palladian]","Provides [4] [Mithrite]","Provides [4] [Hyperium]"],
        "requiredTech": "Blessings of the Mother"
    },
	
	
	
	
	
	
	
	//Broken Lords Tech Boosts
	{
        "name": "Broken Archaeologists",   
		"uniqueTo": "Broken Lords",
        "isNationalWonder": true,
		"cost": 1,
		"requiredTech": "Archaeologist",
        "uniques": ["Unsellable","[+5 Science] per [1] population [in all cities]"]
    },
	{
        "name": "Chapel of Penitence",   
		"uniqueTo": "Broken Lords",
		"cost": 1,
		"requiredTech": "Penitent Chapel",
        "uniques": ["Unsellable","All newly-trained [All] units in this city receive the [Medic] promotion"]
    },
	{
        "name": "Dust Synchronizer",    
		"uniqueTo": "Broken Lords",
		"cost": 1,
		"requiredTech": "Synchronic Temple",
        "uniques": ["Unsellable","All newly-trained [All] units in this city receive the [Synchronized] promotion"]
    },
	//others
	{
        "name": "Altar of Channeling",   
		"uniqueTo": "Broken Lords",
        "isNationalWonder": true,
        "hurryCostModifier": 20,
		"cost": 1500,
		"gold": 5,
		"uniques": ["[+5 Gold] per [1] population [in this city]"],
        "requiredTech": "Altar of Channeling"
    },
	//Cultist Walls   
	{
        "name": "Walls of Faith", 
		"uniqueTo": "Cultists",
        "isNationalWonder": true,
		"cost": 1,
        "cityStrength": 20,
        "cityHealth": 100,
		"uniques": ["Unsellable","Unbuildable"]
    },
	{
        "name": "Shrine of Whispers",  
		"uniqueTo": "Cultists",
        "isNationalWonder": true,
		"cost": 800,
		"maintenence": 4,
		"uniques": ["+[30]% [Science] [in this city]",
		"Consumes [5] [Hyperium]"],
        "requiredTech": "Shrine of Whispers"
    },
	//Cultist Tech Boost     "uniques": ["Free [Cultist] appears"],   //Given to all Cultist Tech Boosts
	{
        "name": "Analyzer",   
		"uniqueTo": "Cultists",
        "isNationalWonder": true,
		"cost": 1,
		"uniques": ["[+1 Science] per [2] population [in this city]","[2] free [Cultist] units appear"],
        "requiredTech": "Destructive Analysis"
    },
	{
        "name": "Legion",   
		"uniqueTo": "Cultists",
        "isNationalWonder": true,
		"cost": 1,
		"uniques": ["New [Military] units start with [15] Experience in this city","[2] free [Cultist] units appear"],
        "requiredTech": "We are Legion"
    },
	{
        "name": "Siblings",   
		"uniqueTo": "Cultists",
        "isNationalWonder": true,
		"cost": 1,
		"uniques": ["New [Military] units start with [30] Experience in this city","[2] free [Cultist] units appear"],
        "requiredTech": "All Beings are Siblings"
    },
	{
        "name": "The Unspoken",   
		"uniqueTo": "Cultists",
        "isNationalWonder": true,
		"cost": 1,
		"uniques": ["[4] free [Cultist] units appear"],
        "requiredTech": "Hand of the Unspoken"
    },
	// Drakken tech boosts & buildings
	{
        "name": "Aura of Leadership",   
		"uniqueTo": "Drakken",
        "isNationalWonder": true,
		"cost": 1,
		"uniques": ["[+1 Culture] [in all cities]","[+1 Science] [in all cities]"],
        "requiredTech": "Aura of Leadership"
    },
	{
        "name": "Oologic Nursery",   
		"uniqueTo": "Drakken",
		"cost": 400,
		"food": 10,
		"uniques": ["Consumes [4] [Titanium]","Consumes [8] Glassteel","New [Military] units start with [15] Experience in this city"],
        "requiredTech": "Oologic Nursery"
    },
	{
        "name": "Tribal Council",   
		"uniqueTo": "Drakken",
        "isNationalWonder": true,
		"cost": 1,
		"uniques": ["[+1 Culture] per [2] population [in this city]"],
        "requiredTech": "Tribal Council"
    },
	{
        "name": "Auriga Institute",   
		"uniqueTo": "Drakken",
		"cost": 800,
		"culture": 10,
		"happiness": 10,
		"uniques": ["Consumes [4] [Mithrite]"],
        "requiredTech": "Auriga Institute"
    },
	{
        "name": "Eye of the Endless",   //needs testing
		"uniqueTo": "Drakken",
        "isNationalWonder": true,
		"cost": 1,
		"uniques": ["All newly-trained [All] units receive the [Endless Eye] promotion"],
        "requiredTech": "Eye of the Endless"
    },
	
	
	
	
	
	
	
	
	
	
	//General Tech boosts
	
	{
        "name": "Glassteel Factory", 
        "isNationalWonder": true, 
		"cost": 1,
        "uniques": ["Provides [10] [Glassteel]"],
        "requiredTech": "Exotic Alloys"
    },
	{
        "name": "Titanium Factory", 
        "isNationalWonder": true, 
		"cost": 1,
        "uniques": ["Provides [10] [Titanium]"],
        "requiredTech": "Exotic Armor"
    },
	{
        "name": "Bread and Circuses", 
        "isNationalWonder": true, 
		"cost": 1,
        "uniques": ["Unhappiness from population decreased by [10]%"],
        "requiredTech": "Bread and Circuses"
    },
	{
        "name": "Meritocratic Promotion",   
        "isNationalWonder": true, 
		"cost": 1,
        "uniques": ["Free [Infantry] appears","Free [Ranger] appears","Free [Cavalry] appears","Free [Flying] appears","Free [Support] appears"],
        "requiredTech": "Meritocratic Promotion"
    },
	{
        "name": "Volunteers", 
        "isNationalWonder": true, 
		"cost": 1,
        "uniques": ["Cost of purchasing items in cities reduced by [25]%"],
        "requiredTech": "Prisoners, Slaves, and Volunteers"
    },
	{
        "name": "Brigade System",
        "isNationalWonder": true, 
		"cost": 1,
		"uniques": ["All newly-trained [All] units receive the [Brigade] promotion"],
        "requiredTech": "Brigade System"
    },
	{
        "name": "Signal Corps",
        "isNationalWonder": true, 
		"cost": 1,
		"uniques": ["-[15]% [Military] unit maintenance costs"],
        "requiredTech": "Signal Corps"
    },
	{
        "name": "Mercenary Corps",     //NEEDS UPDATE FOR T2 UNITS
        "isNationalWonder": true, 
		"cost": 1,
        "uniques": ["Free [Infantry] appears","Free [Ranger] appears","Free [Cavalry] appears","Free [Flying] appears","Free [Support] appears"],
        "requiredTech": "Mercenary Corps"
    },
	{
        "name": "State-Approved Theatre",
        "isNationalWonder": true, 
		"cost": 1,
		"uniques": ["Unhappiness from population decreased by [25]%"],
        "requiredTech": "State-Approved Theatre"
    },
	{
        "name": "Difference Engine",
        "isNationalWonder": true, 
		"cost": 1,
		"uniques": ["+[50]% [Science] [in all cities]"],
        "requiredTech": "Difference Engine"
    },
	{
        "name": "Dust-Driven Distillery",
        "isNationalWonder": true, 
		"cost": 1,
		"uniques": ["+[50]% [Gold] [in all cities]"],
        "requiredTech": "Dust-Driven Distillery"
    },
	{
        "name": "Endless Alloys",
        "isNationalWonder": true, 
		"cost": 1,
		"uniques": ["+[50]% [Production] [in all cities]"],
        "requiredTech": "Endless Alloys"
    },
	{
        "name": "Self-Driving Plows",
        "isNationalWonder": true, 
		"cost": 1,
		"uniques": ["+[50]% [Food] [in all cities]"],
        "requiredTech": "Self-Driving Plows"
    },
	{
        "name": "Serum of Iteru",
        "isNationalWonder": true, 
		"cost": 1,
		"uniques": ["All newly-trained [All] units in this city receive the [Serum of Iteru] promotion"],
        "requiredTech": "Serum of Iteru"
    },
	{
        "name": "United Empires Council",
        "isNationalWonder": true, 
		"cost": 1,
		"uniques": ["+[50]% [Culture] [in all cities]"],
        "requiredTech": "United Empires Council"
    },
	
	
	
	
	
	
	//Extractors
	//Strategics
	{
        "name": "Titanium Extractor",
        "hurryCostModifier": 20,
		"cost": 60,
        "uniques": ["Must have an owned [Titanium] within [3] tiles","Provides [8] [Titanium]","+[20]% [Science] [in this city]"],
        "requiredTech": "Alchemist's Furnace"
    },
	{
        "name": "Glassteel Extractor",
        "hurryCostModifier": 20,
		"cost": 60,
        "uniques": ["Must have an owned [Glassteel] within [3] tiles","Provides [8] [Glassteel]","+[20]% [Gold] [in this city]"],
        "requiredTech": "Alchemist's Furnace"
    },
	{
        "name": "Adamantian Extractor",
        "hurryCostModifier": 20,
		"cost": 60,
        "uniques": ["Must have an owned [Adamantian] within [3] tiles","Provides [8] [Adamantian]","+[20]% [Production] [in this city]"],
        "requiredTech": "Smelting Station"
    },
	{
        "name": "Palladian Extractor",
        "hurryCostModifier": 20,
		"cost": 60,
        "uniques": ["Must have an owned [Palladian] within [3] tiles","Provides [8] [Palladian]","+[20]% [Food] [in this city]"],
        "requiredTech": "Smelting Station"
    },
	{
        "name": "Mithrite Extractor",
        "hurryCostModifier": 20,
		"cost": 60,
        "uniques": ["Must have an owned [Mithrite] within [3] tiles","Provides [8] [Mithrite]",
		"+[15]% [Production] [in this city]","+[15]% [Gold] [in this city]"],
        "requiredTech": "Rare Metal Foundry"
    },
	{
        "name": "Hyperium Extractor",
        "hurryCostModifier": 20,
		"cost": 60,
        "uniques": ["Must have an owned [Hyperium] within [3] tiles","Provides [8] [Hyperium]",
		"+[15]% [Science] [in this city]","+[15]% [Food] [in this city]"],
        "requiredTech": "Rare Metal Foundry"
    },
	//"Luxes"
	{
        "name": "Dye Extractor",
        "hurryCostModifier": 20,
		"cost": 60,
        "resourceBonusStats": {"happiness": 2},
        "uniques": ["Must have an owned [Dye] within [3] tiles","+[50]% [Culture] [in this city]"],
        "requiredTech": "Open-Pit Mine"
    },
	{
        "name": "Emerald Extractor",  //defense bonus not working?
        "hurryCostModifier": 20,
		"cost": 60,
        "resourceBonusStats": {"happiness": 2},
        "uniques": ["Must have an owned [Emerald] within [3] tiles","Defensive buildings in this city are 30% more effective"],
        "requiredTech": "Open-Pit Mine"
    },
	{
        "name": "Bronze Extractor",
        "hurryCostModifier": 20,
		"cost": 60,
        "resourceBonusStats": {"happiness": 2},
        "uniques": ["Must have an owned [Bronze] within [3] tiles","+[50]% [Gold] [in this city]"],
        "requiredTech": "Open-Pit Mine"
    },
	{
        "name": "Spice Extractor",
        "hurryCostModifier": 20,
		"cost": 60,
        "resourceBonusStats": {"happiness": 2},
        "uniques": ["Must have an owned [Spice] within [3] tiles","+[50]% [Food] [in this city]"],
        "requiredTech": "Open-Pit Mine"
    },
	{
        "name": "Wine Extractor",
        "hurryCostModifier": 20,
		"cost": 60,
        "resourceBonusStats": {"happiness": 2},
		"happiness": 10,
        "uniques": ["Must have an owned [Wine] within [3] tiles"],
        "requiredTech": "Open-Pit Mine"
    },
	{
        "name": "Blood Crystal Extractor",
        "hurryCostModifier": 20,
		"cost": 300,
        "resourceBonusStats": {"happiness": 2},
        "uniques": ["Must have an owned [Blood Crystal] within [3] tiles","All newly-trained [All] units in this city receive the [Blood Crystal] promotion"],
        "requiredTech": "Reaping Station"
    },
	{
        "name": "Grassilk Extractor",
        "hurryCostModifier": 20,
		"cost": 300,
        "resourceBonusStats": {"happiness": 2},
        "uniques": ["Must have an owned [Grassilk] within [3] tiles","[+1 Gold] per [1] population [in this city]"],
        "requiredTech": "Reaping Station"
    },
	{
        "name": "Moon Leaf Extractor",
        "hurryCostModifier": 20,
		"cost": 300,
        "resourceBonusStats": {"happiness": 2},
        "uniques": ["Must have an owned [Moon Leaf] within [3] tiles","+[50]% [Science] [in this city]"],
        "requiredTech": "Reaping Station"
    },
	{
        "name": "Quicksilver Extractor",
        "hurryCostModifier": 20,
		"cost": 300,
        "resourceBonusStats": {"happiness": 2},
        "uniques": ["Must have an owned [Quicksilver] within [3] tiles","New [Military] units start with [30] Experience in this city"],
        "requiredTech": "Reaping Station"
    },
	{
        "name": "Titan Bones Extractor",
        "hurryCostModifier": 20,
		"cost": 300,
        "resourceBonusStats": {"happiness": 2},
        "uniques": ["Must have an owned [Titan Bones] within [3] tiles","+[50]% [Production] [in this city]"],
        "requiredTech": "Reaping Station"
    },
	{
        "name": "Dust Orchid Extractor",
        "hurryCostModifier": 20,
		"cost": 600,
        "resourceBonusStats": {"happiness": 2},
        "uniques": ["Must have an owned [Dust Orchid] within [3] tiles","+[10]% [Production] [in this city]","+[10]% [Science] [in this city]","+[10]% [Gold] [in this city]","+[10]% [Culture] [in this city]"],
        "requiredTech": "Advanced Harvester"
    },
	{
        "name": "Dustwater Extractor",
        "hurryCostModifier": 20,
		"cost": 600,
        "resourceBonusStats": {"happiness": 2},
        "uniques": ["Must have an owned [Dustwater] within [3] tiles","+[100]% [Gold] [in this city]"],
        "requiredTech": "Advanced Harvester"
    },
	{
        "name": "Hydromiel Extractor",
        "hurryCostModifier": 20,
		"cost": 600,
        "resourceBonusStats": {"happiness": 2},
        "uniques": ["Must have an owned [Hydromiel] within [3] tiles","-[25]% [Military] unit maintenance costs"],
        "requiredTech": "Advanced Harvester"
    },
	{
        "name": "Pixie Blood Extractor",
        "hurryCostModifier": 20,
		"cost": 600,
		"cityStrength": 50,
        "resourceBonusStats": {"happiness": 2},
        "uniques": ["Must have an owned [Pixie Blood] within [3] tiles"],
        "requiredTech": "Advanced Harvester"
    },
	{
        "name": "Redsang Extractor",
        "hurryCostModifier": 20,
		"cost": 600,
        "resourceBonusStats": {"happiness": 2},
        "uniques": ["Must have an owned [Redsang] within [3] tiles","[Military] units gain [20]% more Experience from combat"],
        "requiredTech": "Advanced Harvester"
    },
	
	
	
	
	
	
	//Era I
	{
        "name": "Dust Filtration",
        "hurryCostModifier": 20,
		"cost": 75,
        "uniques": ["Must have an owned [Water] within [3] tiles","[+3 Gold] from [Coast] tiles in this city","[+3 Gold] from [Lakes] tiles in this city","[+3 Gold] from [Ocean] tiles in this city"],
        "requiredTech": "Aquapulvistics"
    },
	{
        "name": "Dust Dredger",
        "hurryCostModifier": 20,
		"cost": 75,
        "uniques": ["Must have an owned [River] within [3] tiles","[+2 Gold] from [River] tiles in this city"],
        "requiredTech": "Aquapulvistics"
    },
	{
        "name": "Sewer System",
        "hurryCostModifier": 20,
		"cost": 75,
		"maintenance": 1,
		"happiness": 5,
		"culture": 2,
        "requiredTech": "Sewer System"
    },
	{
        "name": "Seed Storage",
        "hurryCostModifier": 20,
		"cost": 75,
		"maintenance": 1,
		"food": 5,
		"uniques": ["+[15]% [Food] [in this city]"],
        "requiredTech": "Cultivation"
    },
	{
        "name": "Husbandry Center",
        "isNationalWonder": true,
        "hurryCostModifier": 20,
		"cost": 150,
		"maintenance": 4,
		"uniques": ["[+1 Food] per [2] population [in this city]"],
        "requiredTech": "Cultivation"
    },
	{
        "name": "Empire Mint",
        "hurryCostModifier": 20,
		"cost": 75,
		"gold": 5,
		"uniques": ["+[15]% [Gold] [in this city]"],
        "requiredTech": "Empire Mint"
    },
	{
        "name": "Stronghold Architecture",
        "hurryCostModifier": 20,
		"cost": 75,
        "cityStrength": 20,
        "cityHealth": 100,
        "requiredTech": "Military Science"
    },
	{
        "name": "Mill Foundry",
        "hurryCostModifier": 20,
		"cost": 75,
		"production": 5,
		"maintenance": 1,
		"uniques": ["+[15]% [Production] [in this city]"],
        "requiredTech": "Mill Foundry"
    },
	{
        "name": "Public Library",
        "hurryCostModifier": 20,
		"cost": 75,
		"science": 5,
		"maintenance": 1,
		"uniques": ["+[15]% [Science] [in this city]"],
        "requiredTech": "Public Library"
    },
	{
        "name": "Center of Minerology",
        "isNationalWonder": true,
        "hurryCostModifier": 20,
		"cost": 150,
		"maintenance": 4,
		"uniques": ["[+1 Science] per [2] population [in this city]"],
        "requiredTech": "Topography"
    },
	{
        "name": "Geomic Lab",  
        "hurryCostModifier": 20,
		"cost": 75,
		"maintenance": 1,
		"uniques": ["[+2 Science] from [Tundra] tiles in this city","[+2 Science] from [Glassteel] tiles in this city","[+2 Science] from [Titanium] tiles in this city","[+2 Science] from [Adamantian] tiles in this city","[+2 Science] from [Palladian] tiles in this city","[+2 Science] from [Mithrite] tiles in this city","[+2 Science] from [Hyperium] tiles in this city",
		"[+2 Science] from [Azotic Exotics] tiles in this city","[+2 Science] from [Black Dust] tiles in this city","[+2 Science] from [Botanical Garden] tiles in this city","[+2 Science] from [Chromatic Land] tiles in this city","[+2 Science] from [Crystal Flowers] tiles in this city","[+2 Science] from [Dragon Tree] tiles in this city","[+2 Science] from [Earthspine] tiles in this city","[+2 Science] from [Earth Tower] tiles in this city","[+2 Science] from [Geothermal Pit] tiles in this city","[+2 Science] from [Geysers] tiles in this city","[+2 Science] from [Ice Sculptures] tiles in this city","[+2 Science] from [Lava Chimneys] tiles in this city","[+2 Science] from [Lava Geyser] tiles in this city","[+2 Science] from [Life Tree] tiles in this city","[+2 Science] from [Meteor Fields] tiles in this city","[+2 Science] from [Moss Pearls] tiles in this city","[+2 Science] from [Mutant Marsh] tiles in this city","[+2 Science] from [Mychordia] tiles in this city","[+2 Science] from [Spiral Rock Peel] tiles in this city","[+2 Science] from [Stasis Pillar] tiles in this city","[+2 Science] from [Wizard Stone] tiles in this city"],
        "requiredTech": "Topography"
    },
	
	//Era II
	{
        "name": "Alchemy Workshop",
        "hurryCostModifier": 20,
		"cost": 250,
		"science": 10,
		"maintenance": 2,
		"uniques": ["Consumes [4] [Titanium]","+[20]% [Science] [in this city]"],
        "requiredTech": "Alchemy Workshop"
    },
	{
        "name": "Irrigation Network",
        "hurryCostModifier": 20,
		"cost": 250,
        "uniques": ["Must have an owned [River] within [3] tiles","[+3 Food] from [River] tiles in this city"],
        "requiredTech": "Aquacultural Science"
    },
	{
        "name": "Fish Farm",
        "hurryCostModifier": 20,
		"cost": 250,
        "uniques": ["Must have an owned [Water] within [3] tiles","[+3 Food] from [Coast] tiles in this city","[+3 Food] from [Lakes] tiles in this city","[+3 Food] from [Ocean] tiles in this city"],
        "requiredTech": "Aquacultural Science"
    },
	{
        "name": "Central Market",
        "hurryCostModifier": 20,
		"cost": 250,
		"happiness": 5,
		"maintenance": 2,
		"uniques": ["Consumes [2] [Glassteel]","+[10]% [Food] [in this city]","+[10]% [Gold] [in this city]"],
        "requiredTech": "Central Market"
    },
	{
        "name": "Conscription Center",
        "hurryCostModifier": 20,
		"cost": 250,
		"maintenance": 2,
		"uniques": ["New [Military] units start with [15] Experience in this city"],
        "requiredTech": "Citizin Armies"
    },
	{
        "name": "Defensive Wards",
        "isNationalWonder": true,
        "hurryCostModifier": 20,
		"cost": 600,
        "cityHealth": 100,
		"maintenance": 2,
		"uniques": ["Consumes [4] [Glassteel]"]
        "requiredTech": "Citizin Armies"
    },
	{
        "name": "Glory of Empire",
        "hurryCostModifier": 20,
		"cost": 250,
		"culture": 5,
		"maintenence": 3,
		"uniques": ["[+1 Culture] per [2] population [in this city]"],
        "requiredTech": "Glory of Empire"
    },
	{
        "name": "Canal System",
        "hurryCostModifier": 20,
		"cost": 250,
		"maintenence": 2,
		"uniques": ["[+2 Production] from [Snow] tiles in this city","[+2 Production] from [Forest] tiles in this city","[+2 Production] from [Jungle] tiles in this city","[+2 Production] from [Marsh] tiles in this city","[+2 Production] from [Oasis] tiles in this city","[+2 Production] from [Flood plains] tiles in this city","[+2 Production] from [Atoll] tiles in this city",
		"[+2 Production] from [Caldera Lake] tiles in this city","[+2 Production] from [Clay] tiles in this city","[+2 Production] from [Dragon Tree] tiles in this city","[+2 Production] from [Earth Tower] tiles in this city","[+2 Production] from [Fumarole] tiles in this city","[+2 Production] from [Geothermal Pit] tiles in this city","[+2 Production] from [Geysers] tiles in this city","[+2 Production] from [Golden Tree] tiles in this city","[+2 Production] from [Igloo Larvae] tiles in this city","[+2 Production] from [Lava Geyser] tiles in this city","[+2 Production] from [Massive Tree] tiles in this city","[+2 Production] from [Meteor Fields] tiles in this city","[+2 Production] from [Mineral Rich] tiles in this city","[+2 Production] from [Ruby Cactus Fields] tiles in this city","[+2 Production] from [Rumbling Stones] tiles in this city","[+2 Production] from [Spiral Rock Peel] tiles in this city","[+2 Production] from [Steel Stalks] tiles in this city","[+2 Production] from [Steppe Soil] tiles in this city","[+2 Production] from [Weaver Worms] tiles in this city","[+2 Production] from [Wizard Stone] tiles in this city"],
        "requiredTech": "Hydrology"
    },
	{
        "name": "Canal Locks",
        "isNationalWonder": true,
        "hurryCostModifier": 20,
		"cost": 600,
		"maintenence": 4,
		"uniques": ["Consumes [4] [Titanium]","[+2 Production] per [1] population [in this city]"],
        "requiredTech": "Hydrology"
    },
	{
        "name": "Right of Way",
        "isNationalWonder": true,
        "hurryCostModifier": 20,
		"cost": 250,
		"maintenance": 3,
		"uniques": ["-[10]% [Military] unit maintenance costs"]
        "requiredTech": "Imperial Highways"
    },
	{
        "name": "Watchtower",   //add Mykaran Watchtower!
        "hurryCostModifier": 20,
		"cost": 250,
        "cityHealth": 50,
        "cannotBeBuiltWith": "Lookout Tower",
        "requiredTech": "Imperial Highways"
    },
	{
        "name": "Lumber Mill",
        "hurryCostModifier": 20,
		"cost": 250,
		"maintenence": 2,
		"uniques": ["Consumes [4] [Titanium]","[+2 Production] from [Forest] tiles in this city","[+2 Production] from [Jungle] tiles in this city","[+2 Production] from [Marsh] tiles in this city","[+2 Production] from [Oasis] tiles in this city","[+2 Production] from [Atoll] tiles in this city"]
		"requiredTech": "Management Sciences"
    },
	{
        "name": "Apprenticeship Registry",
        "hurryCostModifier": 20,
		"cost": 250,
		"production": 5,
		"maintenence": 2,
		"uniques": ["Consumes [4] [Titanium]"],
        "requiredTech": "Management Sciences"
    },
	{
        "name": "Public Granary",
        "hurryCostModifier": 20,
		"cost": 250,
		"food": 15,
		"maintenence": 2,
		"uniques": ["Consumes [4] [Glassteel]"],
        "requiredTech": "Public Granary"
    },
	
	
	
	
	
	
	
	//Era III
	{
        "name": "Imperial Kennels",
        "hurryCostModifier": 20,
		"cost": 600,
        "cityHealth": 200,
		"maintenance": 1,
		"uniques": ["Consumes [4] [Titanium]","New [Military] units start with [15] Experience in this city"],
        "requiredTech": "Borough Government"
    },
	{
        "name": "Materials Hoard",
        "hurryCostModifier": 20,
		"cost": 600,
        "cityHealth": 200,
		"cityStrength": 20,
		"maintenance": 1,
		"uniques": ["Consumes [4] [Titanium]"],
        "requiredTech": "Borough Government"
    },
	{
        "name": "Medical Center",
        "hurryCostModifier": 20,
		"cost": 600,
		"maintenance": 2,
		"uniques": ["Consumes [4] [Palladian]","+[15]% growth [in this city]"],
        "requiredTech": "Borough Government"
    },
	{
        "name": "Cargo Docks", 
		"cost": 600,
		"happiness": 5,
		"gold": 3,
        "uniques": ["Must be next to [Coast]","[+2 Production] from [Coast] tiles in this city","[+2 Production] from [Lakes] tiles in this city","[+2 Production] from [Ocean] tiles in this city"],
        "requiredTech": "Cargo Docks"
    },
	{
        "name": "Dust Depository", 
		"cost": 600,
        "uniques": ["Consumes [4] [Glassteel]","[+2 Gold] per [1] population [in this city]"],
        "requiredTech": "Dust Alchemy"
    },
	{
        "name": "Dust Transmuter",    
		"cost": 600,
        "isNationalWonder": true,
        "uniques": ["Consumes [6] [Glassteel]",
		"[+2 Gold] from every [Coast]","[+2 Gold] from every [River]","[+2 Gold] from every [Jungle]","[+2 Gold] from every [Desert]","[+2 Gold] from every [Lakes]","[+2 Gold] from every [Plains]","[+2 Gold] from every [Ocean]",
		"[+1 Gold] from every [Dye]","[+1 Gold] from every [Emerald]","[+1 Gold] from every [Bronze]","[+1 Gold] from every [Spice]","[+1 Gold] from every [Wine]",
		"[+1 Gold] from every [Blood Crystal]","[+1 Gold] from every [Grassilk]","[+1 Gold] from every [Moon Leaf]","[+1 Gold] from every [Quicksilver]","[+1 Gold] from every [Titan Bones]",
		"[+1 Gold] from every [Dust Orchid]","[+1 Gold] from every [Dustwater]","[+1 Gold] from every [Hydromiel]","[+1 Gold] from every [Pixie Blood]","[+1 Gold] from every [Redsang]",
		"[+1 Gold] from every [Black Dust]","[+1 Gold] from every [Botanical Garden]","[+1 Gold] from every [Caldera Lake]","[+1 Gold] from every [Chromatic Land]","[+1 Gold] from every [Clay]","[+1 Gold] from every [Crystal Flowers]","[+1 Gold] from every [Dragon Tree]","[+1 Gold] from every [Earthspine]","[+1 Gold] from every [Escaped Specimens]","[+1 Gold] from every [Golden Tree]","[+1 Gold] from every [Hidden Springs]","[+1 Gold] from every [Lava Chimneys]","[+1 Gold] from every [Mutant Marsh]","[+1 Gold] from every [Hidden Oasis]","[+1 Gold] from every [Ruby Cactus Fields]","[+1 Gold] from every [Rumbling Stones]","[+1 Gold] from every [Salt Desert]","[+1 Gold] from every [Stasis Pillar]","[+1 Gold] from every [Steel Stalks]","[+1 Gold] from every [Weaver Worms]"],
        "requiredTech": "Dust Alchemy"
    },
	{
        "name": "Dust Refinery", 
		"cost": 600,
		"gold": 15,
        "uniques": ["Consumes [6] [Glassteel]"],
        "requiredTech": "Dust Refinery"
    },
	{
        "name": "Large-Scale Aquatic Center", 
		"cost": 600,
		"maintenance": 4,
        "uniques": ["Must have an owned [Water] within [3] tiles","Consumes [6] [Titanium]","[+2 Science] from [Water] tiles in this city"],
        "requiredTech": "Fluid Biomechanics"
    },
	{
        "name": "Hydromatic Laboratory",
        "hurryCostModifier": 20,
		"cost": 600,
		"maintenance": 4,
        "uniques": ["Must have an owned [River] within [3] tiles","Consumes [6] [Titanium]","[+3 Science] from [River] tiles in this city"],
        "requiredTech": "Fluid Biomechanics"
    },
	{
        "name": "Lookout Tower",   //add Mykaran Lookout!
        "hurryCostModifier": 20,
		"cost": 350,
        "cannotBeBuiltWith": "Watchtower",  //+1 vision
		"uniques": ["All newly-trained [All] units in this city receive the [Scouting I] promotion"],
        "requiredTech": "Highway Outposts"
    },
	{
        "name": "Lava Works", 
		"cost": 600,
		"maintenance": 4,
        "uniques": ["Must have an owned [Desert] within [3] tiles","Consumes [4] [Titanium]","Consumes [4] [Glassteel]",
		"[+3 Production] from [Desert] tiles in this city","[+3 Science] from [Desert] tiles in this city"],
        "requiredTech": "Magma Hydraulics"
    },
	{
        "name": "Plow Factory",   
        "hurryCostModifier": 20,
		"cost": 600,
		"uniques": ["Consumes [6] [Glassteel]","Consumes [4] [Palladian]","[+1 Food] from [Land]"],
        "requiredTech": "Plow Factory"
    },
	{
        "name": "National Museum",   
        "hurryCostModifier": 20,
		"cost": 600,
		"culture": 10,
		"maintenence": 4,
		"uniques": ["[+1 Culture] per [1] population [in this city]","Consumes [4] [Palladian]","Consumes [4] [Adamantian]"],
        "requiredTech": "Public Works"
    },
	{
        "name": "National Arena",   
        "hurryCostModifier": 20,
		"cost": 1200,
        "isNationalWonder": true,
		"maintenence": 8,
		"uniques": ["Consumes [6] [Titanium]","+[50]% [Culture] [in this city]"],
        "requiredTech": "Public Works"
    },
	{
        "name": "Advanced Alchemy Lab",
        "hurryCostModifier": 20,
		"cost": 600,
		"maintenance": 4,
		"science": 5,
		"uniques": ["Consumes [4] [Titanium]","[+1 Science] per [1] population [in this city]"],
        "requiredTech": "Statistical Methods"
    },
	{
        "name": "Cryometric Monitors",  
        "hurryCostModifier": 20,
		"cost": 1200,
        "isNationalWonder": true,
		"maintenance": 8,
		"uniques": ["[+5 Science] from [Bonus resource] tiles in this city"],
		"requiredTech": "Statistical Methods"
    },
	{
        "name": "Bells and Whistles",  
        "hurryCostModifier": 20,
		"cost": 600,
        "cityHealth": 50,
		"cityStrength": 30,
		"maintenance": 6,
		"uniques": ["Consumes [4] [Palladian]"],
		"requiredTech": "Unexpected Allies"
    },
	
	
	
	
	//Era IV
	{
        "name": "Wyrm Farm",
        "hurryCostModifier": 20,
		"cost": 1200,
		"maintenance": 7,
		"food": 10,
		"uniques": ["Consumes [4] [Adamantian]","Consumes [4] [Palladian]"],
        "requiredTech": "Anaerobic Mycrobiology"
    },
	{
        "name": "Automated Production",
        "hurryCostModifier": 20,
		"cost": 1200,
		"maintenence": 7,
		"uniques": ["Consumes [4] [Titanium]","Consumes [8] [Adamantian]",
		"[+3 Production] from [Snow] tiles in this city","[+3 Production] from [Forest] tiles in this city","[+3 Production] from [Jungle] tiles in this city","[+3 Production] from [Marsh] tiles in this city","[+3 Production] from [Oasis] tiles in this city","[+3 Production] from [Flood plains] tiles in this city","[+3 Production] from [Atoll] tiles in this city",
		"[+3 Production] from [Caldera Lake] tiles in this city","[+3 Production] from [Clay] tiles in this city","[+3 Production] from [Dragon Tree] tiles in this city","[+3 Production] from [Earth Tower] tiles in this city","[+3 Production] from [Fumarole] tiles in this city","[+3 Production] from [Geothermal Pit] tiles in this city","[+3 Production] from [Geysers] tiles in this city","[+3 Production] from [Golden Tree] tiles in this city","[+3 Production] from [Igloo Larvae] tiles in this city","[+3 Production] from [Lava Geyser] tiles in this city","[+3 Production] from [Massive Tree] tiles in this city","[+3 Production] from [Meteor Fields] tiles in this city","[+3 Production] from [Mineral Rich] tiles in this city","[+3 Production] from [Ruby Cactus Fields] tiles in this city","[+3 Production] from [Rumbling Stones] tiles in this city","[+3 Production] from [Spiral Rock Peel] tiles in this city","[+3 Production] from [Steel Stalks] tiles in this city","[+3 Production] from [Steppe Soil] tiles in this city","[+3 Production] from [Weaver Worms] tiles in this city","[+3 Production] from [Wizard Stone] tiles in this city"],
        "requiredTech": "Borer's Guild"
    },
	{
        "name": "Mining Rights",
        "hurryCostModifier": 20,
		"cost": 1200,
		"maintenance": 7,
		"uniques": ["Consumes [4] [Titanium]","Consumes [8] [Adamantian]",
		"Provides [10] [Glassteel]","Provides [10] [Titanium]","Provides [10] [Adamantian]","Provides [10] [Palladian]","Provides [10] [Mithrite]","Provides [10] [Hyperium]"],
        "requiredTech": "Borer's Guild"
    },
	{
        "name": "Army Manual",
        "hurryCostModifier": 20,
		"cost": 1200,
		"maintenance": 7,
		"uniques": ["Consumes [2] [Hyperium]","New [Military] units start with [30] Experience in this city"],
        "requiredTech": "Civic Instruction"
    },
	{
        "name": "National Military College",
        "hurryCostModifier": 20,
		"cost": 2500,
        "isNationalWonder": true,
		"maintenance": 15,
		"uniques": ["Consumes [6] [Palladian]","All newly-trained [All] units in this city receive the [Trained] promotion"],
        "requiredTech": "Civic Instruction"
    },
	{
        "name": "Imperial Studies",  
        "hurryCostModifier": 20,
		"cost": 1200,
		"maintenance": 7,
		"uniques": ["Consumes [2] [Hyperium]","Consumes [12] [Titanium]",
		"[+2 Science] from [Tundra] tiles in this city","[+2 Science] from [Glassteel] tiles in this city","[+2 Science] from [Titanium] tiles in this city","[+2 Science] from [Adamantian] tiles in this city","[+2 Science] from [Palladian] tiles in this city","[+2 Science] from [Mithrite] tiles in this city","[+2 Science] from [Hyperium] tiles in this city",
		"[+2 Science] from [Azotic Exotics] tiles in this city","[+2 Science] from [Black Dust] tiles in this city","[+2 Science] from [Botanical Garden] tiles in this city","[+2 Science] from [Chromatic Land] tiles in this city","[+2 Science] from [Crystal Flowers] tiles in this city","[+2 Science] from [Dragon Tree] tiles in this city","[+2 Science] from [Earthspine] tiles in this city","[+2 Science] from [Earth Tower] tiles in this city","[+2 Science] from [Geothermal Pit] tiles in this city","[+2 Science] from [Geysers] tiles in this city","[+2 Science] from [Ice Sculptures] tiles in this city","[+2 Science] from [Lava Chimneys] tiles in this city","[+2 Science] from [Lava Geyser] tiles in this city","[+2 Science] from [Life Tree] tiles in this city","[+2 Science] from [Meteor Fields] tiles in this city","[+2 Science] from [Moss Pearls] tiles in this city","[+2 Science] from [Mutant Marsh] tiles in this city","[+2 Science] from [Mychordia] tiles in this city","[+2 Science] from [Spiral Rock Peel] tiles in this city","[+2 Science] from [Stasis Pillar] tiles in this city","[+2 Science] from [Wizard Stone] tiles in this city"],
        "requiredTech": "Imperial Funding"
    },
	{
        "name": "Production Line",
        "hurryCostModifier": 20,
		"cost": 1200,
		"maintenance": 7,
		"uniques": ["Consumes [4] [Titanium]","Consumes [4] [Adamantian]","[+2 Production] per [1] population [in this city]"],
        "requiredTech": "Industrial Processing"
    },
	{
        "name": "National Craftworks",
        "hurryCostModifier": 20,
		"cost": 2500,
        "isNationalWonder": true,
		"maintenance": 15,
		"uniques": ["Consumes [8] [Adamantian]",
		"[+3 Science] from every [Dye Extractor]","[+3 Production] from every [Emerald Extractor]","[+3 Gold] from every [Bronze Extractor]","[+3 Food] from every [Spice Extractor]","[+3 Culture] from every [Wine Extractor]",
		"[+3 Culture] from every [Blood Crystal Extractor]","[+3 Gold] from every [Grassilk Extractor]","[+3 Science] from every [Moon Leaf Extractor]","[+3 Food] from every [Quicksilver Extractor]","[+3 Production] from every [Titan Bones Extractor]",
		"[+3 Science] from every [Dust Orchid Extractor]","[+3 Gold] from every [Dustwater Extractor]","[+3 Food] from every [Hydromiel Extractor]","[+3 Culture] from every [Pixie Blood Extractor]","[+3 Production] from every [Redsang Extractor]"],
        "requiredTech": "Industrial Processing"
    },
	{
        "name": "Refrigeration Plant",
        "hurryCostModifier": 20,
		"cost": 1200,
		"maintenance": 7,
		"food": 15,
		"uniques": ["Consumes [8] [Glassteel]","Consumes [2] [Palladian]"],
        "requiredTech": "Isolation Sciences"
    },
	{
        "name": "Subterranean Garden",
        "hurryCostModifier": 20,
		"cost": 1200,
		"maintenance": 7,
		"uniques": ["Consumes [8] [Palladian]","Consumes [2] [Glassteel]","+[25]% growth [in this city]"],
        "requiredTech": "Isolation Sciences"
    },
	{
        "name": "Fertilizer Plant",
        "hurryCostModifier": 20,
		"cost": 1200,
		"maintenance": 7,
		"uniques": ["Consumes [8] [Glassteel]","Consumes [4] [Palladian]",
		"[+2 Food] from [Ocean] tiles in this city","[+2 Food] from [Coast] tiles in this city","[+2 Food] from [Plains] tiles in this city","[+2 Food] from [Desert] tiles in this city","[+2 Food] from [Grassland] tiles in this city","[+2 Food] from [Tundra] tiles in this city","[+2 Food] from [Lakes] tiles in this city","[+2 Food] from [Hill] tiles in this city","[+2 Food] from [Forest] tiles in this city","[+2 Food] from [Jungle] tiles in this city","[+2 Food] from [Oasis] tiles in this city","[+2 Food] from [Atoll] tiles in this city",
		"[+2 Food] from [Azotic Exotics] tiles in this city","[+2 Food] from [Black Earth] tiles in this city","[+2 Food] from [Botanical Garden] tiles in this city","[+2 Food] from [Chromatic Land] tiles in this city","[+2 Food] from [Dragon Tree] tiles in this city","[+2 Food] from [Escaped Specimens] tiles in this city","[+2 Food] from [Hidden Springs] tiles in this city","[+2 Food] from [Igloo Larvae] tiles in this city","[+2 Food] from [Life Tree] tiles in this city","[+2 Food] from [Massive Tree] tiles in this city","[+2 Food] from [Moss Pearls] tiles in this city","[+2 Food] from [Mychordia] tiles in this city","[+2 Food] from [Northern Loam] tiles in this city","[+2 Food] from [Hidden Oasis] tiles in this city","[+2 Food] from [Salt Desert] tiles in this city","[+2 Food] from [Steppe Soil] tiles in this city"],
        "requiredTech": "Nutrition Chemistry"
    },
	{
        "name": "Hothouses",
        "hurryCostModifier": 20,
		"cost": 1200,
        "isNationalWonder": true,
		"maintenance": 7,
		"uniques": ["Consumes [8] [Palladian]","Consumes [4] [Palladian]","[+5 Food] [in all cities]"],
        "requiredTech": "Nutrition Chemistry"
    },
	
	//Era V
	
	{
        "name": "Advanced Quarry",
        "hurryCostModifier": 20,
		"cost": 3000,
        "isNationalWonder": true,
		"maintenance": 10,
		"uniques": ["Consumes [4] [Titanium]","Consumes [10] [Adamantian]","[+5 Production] from [Bonus resource] tiles in this city"],
        "requiredTech": "Advanced Quarry"
    },
	{
        "name": "Arts Council",
        "hurryCostModifier": 20,
		"cost": 2000,
        "isNationalWonder": true,
		"maintenance": 10,
		"happiness": 10,
		"uniques": ["Consumes [4] [Glassteel]","Consumes [2] [Mithrite]"],
        "requiredTech": "Arts Council"
    },
	{
        "name": "Arena of Champions",
        "hurryCostModifier": 20,
		"cost": 3000,
        "isNationalWonder": true,
		"maintenance": 20,
		"uniques": ["Consumes [4] [Adamantian]","Consumes [4] [Palladian]","+[50]% [Culture] [in this city]"],
        "requiredTech": "Dust-Enhanced Building"
    },
	{
        "name": "The Octagon",
        "hurryCostModifier": 20,
		"cost": 4000,
        "isNationalWonder": true,
		"maintenance": 40,
		"uniques": ["Consumes [10] [Mithrite]","New [Military] units start with [15] Experience in this city"],
        "requiredTech": "Dust-Enhanced Building"
    },
	{
        "name": "Remotuscope Factory",   //add Mykaran tower!
        "hurryCostModifier": 20,
		"cost": 2000,
        "cityHealth": 50,
        "cannotBeBuiltWith": "Lookout Tower",
		"uniques": ["All newly-trained [All] units in this city receive the [Scouting I] promotion"],
        "requiredTech": "Enlightened Trade"
    },
	{
        "name": "Imperial News Network",  
        "hurryCostModifier": 20,
		"cost": 2000,
		"happiness": 5,
		"food": 10,
		"production": 10,
		"gold": 10,
		"science": 10,
		"culture": 10,
		"maintenance": 10,
		"uniques": ["Consumes [4] [Mithrite]","Consumes [2] [Glassteel]"],
        "requiredTech": "Imperial News Network"
    },
	{
        "name": "Dust Revitalizer",
        "hurryCostModifier": 20,
		"cost": 2000,
		"uniques": ["Consumes [14] [Glassteel]","Consumes [2] [Mithrite]",
		"[+2 Gold] from every [Coast]","[+2 Gold] from every [River]","[+2 Gold] from every [Jungle]","[+2 Gold] from every [Desert]","[+2 Gold] from every [Lakes]","[+2 Gold] from every [Plains]","[+2 Gold] from every [Ocean]",
		"[+1 Gold] from every [Dye]","[+1 Gold] from every [Emerald]","[+1 Gold] from every [Bronze]","[+1 Gold] from every [Spice]","[+1 Gold] from every [Wine]",
		"[+1 Gold] from every [Blood Crystal]","[+1 Gold] from every [Grassilk]","[+1 Gold] from every [Moon Leaf]","[+1 Gold] from every [Quicksilver]","[+1 Gold] from every [Titan Bones]",
		"[+1 Gold] from every [Dust Orchid]","[+1 Gold] from every [Dustwater]","[+1 Gold] from every [Hydromiel]","[+1 Gold] from every [Pixie Blood]","[+1 Gold] from every [Redsang]",
		"[+1 Gold] from every [Black Dust]","[+1 Gold] from every [Botanical Garden]","[+1 Gold] from every [Caldera Lake]","[+1 Gold] from every [Chromatic Land]","[+1 Gold] from every [Clay]","[+1 Gold] from every [Crystal Flowers]","[+1 Gold] from every [Dragon Tree]","[+1 Gold] from every [Earthspine]","[+1 Gold] from every [Escaped Specimens]","[+1 Gold] from every [Golden Tree]","[+1 Gold] from every [Hidden Springs]","[+1 Gold] from every [Lava Chimneys]","[+1 Gold] from every [Mutant Marsh]","[+1 Gold] from every [Hidden Oasis]","[+1 Gold] from every [Ruby Cactus Fields]","[+1 Gold] from every [Rumbling Stones]","[+1 Gold] from every [Salt Desert]","[+1 Gold] from every [Stasis Pillar]","[+1 Gold] from every [Steel Stalks]","[+1 Gold] from every [Weaver Worms]"],      
        "requiredTech": "Improved Dust Alchemics"
    },
	{
        "name": "Advanced Extraction",  
        "hurryCostModifier": 20,
		"cost": 2000,
		"maintenance": 7,
		"uniques": ["Consumes [20] [Glassteel]",
		"[+5 Science] from every [Dye Extractor]","[+5 Production] from every [Emerald Extractor]","[+5 Gold] from every [Bronze Extractor]","[+5 Food] from every [Spice Extractor]","[+5 Culture] from every [Wine Extractor]",
		"[+5 Culture] from every [Blood Crystal Extractor]","[+5 Gold] from every [Grassilk Extractor]","[+5 Science] from every [Moon Leaf Extractor]","[+5 Food] from every [Quicksilver Extractor]","[+5 Production] from every [Titan Bones Extractor]",
		"[+5 Science] from every [Dust Orchid Extractor]","[+5 Gold] from every [Dustwater Extractor]","[+5 Food] from every [Hydromiel Extractor]","[+5 Culture] from every [Pixie Blood Extractor]","[+5 Production] from every [Redsang Extractor]"],
        "requiredTech": "Improved Dust Alchemics"
    },
	{
        "name": "Inoculation Station", 
        "hurryCostModifier": 20,
		"cost": 2000,
        "cityHealth": 50,
        "cityStrength": 50,
		"maintenance": 5,
		"uniques": ["Consumes [6] [Palladian]","Consumes [2] [Hyperium]","New [Military] units start with [45] Experience in this city"],
        "requiredTech": "Inoculation Station"
    },
	{
        "name": "Military Reserves", 
        "hurryCostModifier": 20,
		"cost": 2000,
        "cityHealth": 400,
		"maintenance": 2,
		"uniques": ["Consumes [2] [Adamantian]","Consumes [4] [Titanium]"],
        "requiredTech": "Military Reserves"
    },
	{
        "name": "Aura of Empire",   
        "hurryCostModifier": 20,
		"cost": 2000,
		"culture": 15,
		"maintenence": 10,
		"uniques": ["[+2 Culture] per [1] population [in this city]","Consumes [4] [Palladian]","Consumes [4] [Adamantian]"],
        "requiredTech": "Modernized Administration"
    },
	{
        "name": "Living Lab Tools",
        "hurryCostModifier": 20,
		"cost": 3000,
        "isNationalWonder": true,
		"maintenance": 20,
		"uniques": ["Consumes [12] [Titanium]","Consumes [4] [Hyperium]","+[50]% [Science] [in this city]"],
        "requiredTech": "Scientific Specialization"
    },
	{
        "name": "Climatology Guild", 
        "hurryCostModifier": 20,
		"cost": 3000,
        "isNationalWonder": true,
		"maintenance": 20,
		"uniques": ["Consumes [16] [Titanium]","Consumes [4] [Hyperium]","[+10 Science] [in all cities]"],
        "requiredTech": "Scientific Specialization"
    },
	{
        "name": "Razor Palisades", 
        "hurryCostModifier": 20,
		"cost": 2000,
        "cityStrength": 50,
		"maintenance": 7,
		"uniques": ["Consumes [4] [Titanium]","Consumes [2] [Mithrite]"],
        "requiredTech": "Security Theory"
    },
	{
        "name": "Town Criers",
        "hurryCostModifier": 20,
		"cost": 2000,
		"gold": 20,
		"uniques": ["+[50]% [Gold] [in this city]"],
        "requiredTech": "Town Criers"
    },
	{
        "name": "Volcanic Leecher",
        "hurryCostModifier": 20,
		"cost": 2000,
        "isNationalWonder": true,
        "uniques": ["Must have an owned [Desert] within [3] tiles","Provides [10] [Glassteel]","Provides [10] [Titanium]","Provides [10] [Adamantian]","Provides [10] [Palladian]","Provides [10] [Mithrite]","Provides [10] [Hyperium]"],
        "requiredTech": "Volcanic Leecher"
    },
	
	//Era VI (Science Win)
	
	{
        "name": "Temple of the Earth's Core",
        "isWonder": true,
        "hurryCostModifier": 20,
		"cost": 8000,
		"uniques": ["Triggers victory"],
        "requiredTech": "Temple of the Earth's Core"
    },
	
	
	//Legendary Deeds Era I
    {
        "name": "Visionary Leader",
        "isWonder": true,
        "requiredTech": "Age of Discovery",
		"cost": 500,
		"uniques": ["Defensive buildings in all cities are 33% more effective"],
    },
    {
        "name": "Wealth Harvester",
        "isWonder": true,
        "requiredTech": "Age of Discovery",
		"cost": 500,
		"uniques": ["[+1 Gold] from every [Dye]","[+1 Gold] from every [Emerald]","[+1 Gold] from every [Bronze]","[+1 Gold] from every [Spice]","[+1 Gold] from every [Wine]",
		"[+1 Culture] from every [Dye]","[+1 Culture] from every [Emerald]","[+1 Culture] from every [Bronze]","[+1 Culture] from every [Spice]","[+1 Culture] from every [Wine]",
		"[+1 Science] from every [Dye]","[+1 Science] from every [Emerald]","[+1 Science] from every [Bronze]","[+1 Science] from every [Spice]","[+1 Science] from every [Wine]"],
    },
	{
        "name": "Museum of Auriga",
        "isWonder": true,
        "requiredTech": "Age of Discovery",
		"cost": 500,
		"happiness": 10,
		"uniques": ["+[10]% [Science] [in all cities]","+[10]% [Gold] [in all cities]","Cost of purchasing items in cities reduced by [25]%"],
    },
	//Legendary Deeds Era II
	{
        "name": "Master of Markets",
        "isWonder": true,
        "requiredTech": "Age of Glory",
		"cost": 1000,
		"uniques": ["[+5 Gold] [in all cities]"],
    },
	{
        "name": "Warrior's Warrior",
        "isWonder": true,
        "requiredTech": "Age of Glory",
		"cost": 1000,
		"uniques": ["[Military] units gain the [Morale] promotion"],
    },
	{
        "name": "Industrial Megapole",  
        "isWonder": true,
        "requiredTech": "Age of Glory",
		"cost": 1000,
		"production": 10,
		"uniques": ["+[25]% Production when constructing [Buildings] [in all cities]"],
    },
	//Deeds Era III
    {
        "name": "Market Alchemist",
        "isWonder": true,
        "requiredTech": "Age of Enlightenment",
		"cost": 1500,
		"uniques": ["[+1 Gold] from every [Glassteel]","[+1 Gold] from every [Titanium]","[+1 Gold] from every [Adamantian]","[+1 Gold] from every [Palladian]",
		"[+1 Culture] from every [Glassteel]","[+1 Culture] from every [Titanium]","[+1 Culture] from every [Adamantian]","[+1 Culture] from every [Palladian]",
		"[+1 Science] from every [Glassteel]","[+1 Science] from every [Titanium]","[+1 Science] from every [Adamantian]","[+1 Science] from every [Palladian]"],
    },
	{
        "name": "Leader of Leaders",
        "isWonder": true,
        "requiredTech": "Age of Enlightenment",
		"cost": 1500,
		"cityStrength": 50,
    },
	{
        "name": "Alchemic Institute",  
        "isWonder": true,
        "requiredTech": "Age of Enlightenment",
		"cost": 1500,
		"uniques": ["[+10 Science] [in all cities]"],
    },
	//Deeds Era IV
	{
        "name": "Benevolent Emporer",  
        "isWonder": true,
        "requiredTech": "Age of Industry",
		"cost": 3000,
		"gold": 20,
		"uniques": ["+[50]% [Gold] [in this city]"],
    },
	{
        "name": "Immovable Force",
        "isWonder": true,
        "requiredTech": "Age of Industry",
		"cost": 3000,
		"cityHealth": 300,
    },
	{
        "name": "Throne of Emperors",
        "requiredTech": "Age of Industry",
		"cost": 3000,
		"culture": 20,
		"uniques": ["[+5 Culture] [in all cities]"],
    },
	//Deeds Era V
	{
        "name": "Patriotic Propaganda",
        "isWonder": true,
        "requiredTech": "Age of Heroes",
		"cost": 5000,
		"uniques": ["Unhappiness from population decreased by [25]%"],
    },
	{
        "name": "Hero of Heroes",
        "isWonder": true,
        "requiredTech": "Age of Heroes",
		"cost": 5000,
		"uniques": ["[Military] units gain the [Heroic] promotion"],
    },
	{
        "name": "Reliquary of Auriga",
        "isWonder": true,
        "requiredTech": "Age of Heroes",
		"cost": 5000,
		"gold": 25,
		"uniques": ["-[50]% [Military] unit maintenance costs"],
    },
	//Guardian "Wonders"
	{
        "name": "Guardian of Dust",    
        "isWonder": true, 
		"cost": 2000,
        "uniques": ["Free [Dust Guardian] appears"],
        "requiredTech": "Guardian of Dust"
    },
	{
        "name": "Guardian of Fire",    
        "isWonder": true, 
		"cost": 2000,
        "uniques": ["Free [Fire Guardian] appears"],
        "requiredTech": "Guardian of Fire"
    },
	{
        "name": "Guardian of Earth",    
        "isWonder": true, 
		"cost": 2000,
        "uniques": ["Free [Earth Guardian] appears"],
        "requiredTech": "Guardian of Earth"
    },
	{
        "name": "Guardian of Air",    
        "isWonder": true, 
		"cost": 2000,
        "uniques": ["Free [Air Guardian] appears"],
        "requiredTech": "Guardian of Air"
    },
	{
        "name": "Guardian of Water",    
        "isWonder": true, 
		"cost": 2000,
        "uniques": ["Free [Water Guardian] appears"],
        "requiredTech": "Guardian of Water"
    },
	
	
	
	
	
	
	
	
	
]
